pass_export/__init__.py
pass_export/main.py
pass_export/py.typed
pass_export-1.0.1.dist-info/entry_points.txt
pass_export-1.0.1.dist-info/LICENSE
pass_export-1.0.1.dist-info/WHEEL
pass_export-1.0.1.dist-info/METADATA
pass_export-1.0.1.dist-info/RECORD
