Metadata-Version: 2.1
Name: pass-export
Version: 1.0.1
Summary: This is a command line tool to export and import passwords from/to pass (https://www.passwordstore.org/).
Author-email: erzo <erzo@posteo.de>
Requires-Python: >=3.6
Classifier: Operating System :: POSIX
Classifier: Operating System :: Unix
Classifier: Environment :: Console
Classifier: License :: OSI Approved :: BSD License
Requires-Dist: tox ; extra == "test"
Project-URL: Home, https://gitlab.com/erzo/pass-export
Provides-Extra: test
